[
    {
        "client_msg_id": "0ea7e354-ed65-4c12-866b-bb0657557028",
        "type": "message",
        "text": "we put this one on our stat slides frequently!",
        "user": "U01AGDAUB1S",
        "ts": "1607630608.010400",
        "team": "T01A754ECJZ",
        "user_team": "T01A754ECJZ",
        "source_team": "T01A754ECJZ",
        "user_profile": {
            "avatar_hash": "81afe241c15d",
            "image_72": "https:\/\/avatars.slack-edge.com\/2020-10-02\/1397872543414_81afe241c15daae264e5_72.jpg",
            "first_name": "Brittany",
            "real_name": "Brittany Lindsay",
            "display_name": "Brittany",
            "team": "T01A754ECJZ",
            "name": "bllindsa",
            "is_restricted": false,
            "is_ultra_restricted": false
        },
        "blocks": [
            {
                "type": "rich_text",
                "block_id": "OLzb\/",
                "elements": [
                    {
                        "type": "rich_text_section",
                        "elements": [
                            {
                                "type": "text",
                                "text": "we put this one on our stat slides frequently!"
                            }
                        ]
                    }
                ]
            }
        ],
        "thread_ts": "1607544681.009800",
        "parent_user_id": "U01AA7U2ECA"
    },
    {
        "type": "message",
        "text": "But I love them all!",
        "files": [
            {
                "id": "F01G7B8FWKH",
                "created": 1607630711,
                "timestamp": 1607630711,
                "name": "image.png",
                "title": "image.png",
                "mimetype": "image\/png",
                "filetype": "png",
                "pretty_type": "PNG",
                "user": "U01AGDAUB1S",
                "editable": false,
                "size": 1135637,
                "mode": "hosted",
                "is_external": false,
                "external_type": "",
                "is_public": true,
                "public_url_shared": false,
                "display_as_bot": false,
                "username": "",
                "url_private": "https:\/\/files.slack.com\/files-pri\/T01A754ECJZ-F01G7B8FWKH\/image.png?t=xoxe-1347174488645-1612442201312-1573826913015-453545d9d1a501a4e497d7cb3f5eacde",
                "url_private_download": "https:\/\/files.slack.com\/files-pri\/T01A754ECJZ-F01G7B8FWKH\/download\/image.png?t=xoxe-1347174488645-1612442201312-1573826913015-453545d9d1a501a4e497d7cb3f5eacde",
                "thumb_64": "https:\/\/files.slack.com\/files-tmb\/T01A754ECJZ-F01G7B8FWKH-3e8c6a0428\/image_64.png?t=xoxe-1347174488645-1612442201312-1573826913015-453545d9d1a501a4e497d7cb3f5eacde",
                "thumb_80": "https:\/\/files.slack.com\/files-tmb\/T01A754ECJZ-F01G7B8FWKH-3e8c6a0428\/image_80.png?t=xoxe-1347174488645-1612442201312-1573826913015-453545d9d1a501a4e497d7cb3f5eacde",
                "thumb_360": "https:\/\/files.slack.com\/files-tmb\/T01A754ECJZ-F01G7B8FWKH-3e8c6a0428\/image_360.png?t=xoxe-1347174488645-1612442201312-1573826913015-453545d9d1a501a4e497d7cb3f5eacde",
                "thumb_360_w": 360,
                "thumb_360_h": 360,
                "thumb_480": "https:\/\/files.slack.com\/files-tmb\/T01A754ECJZ-F01G7B8FWKH-3e8c6a0428\/image_480.png?t=xoxe-1347174488645-1612442201312-1573826913015-453545d9d1a501a4e497d7cb3f5eacde",
                "thumb_480_w": 480,
                "thumb_480_h": 480,
                "thumb_160": "https:\/\/files.slack.com\/files-tmb\/T01A754ECJZ-F01G7B8FWKH-3e8c6a0428\/image_160.png?t=xoxe-1347174488645-1612442201312-1573826913015-453545d9d1a501a4e497d7cb3f5eacde",
                "thumb_720": "https:\/\/files.slack.com\/files-tmb\/T01A754ECJZ-F01G7B8FWKH-3e8c6a0428\/image_720.png?t=xoxe-1347174488645-1612442201312-1573826913015-453545d9d1a501a4e497d7cb3f5eacde",
                "thumb_720_w": 720,
                "thumb_720_h": 720,
                "thumb_800": "https:\/\/files.slack.com\/files-tmb\/T01A754ECJZ-F01G7B8FWKH-3e8c6a0428\/image_800.png?t=xoxe-1347174488645-1612442201312-1573826913015-453545d9d1a501a4e497d7cb3f5eacde",
                "thumb_800_w": 800,
                "thumb_800_h": 800,
                "thumb_960": "https:\/\/files.slack.com\/files-tmb\/T01A754ECJZ-F01G7B8FWKH-3e8c6a0428\/image_960.png?t=xoxe-1347174488645-1612442201312-1573826913015-453545d9d1a501a4e497d7cb3f5eacde",
                "thumb_960_w": 960,
                "thumb_960_h": 960,
                "thumb_1024": "https:\/\/files.slack.com\/files-tmb\/T01A754ECJZ-F01G7B8FWKH-3e8c6a0428\/image_1024.png?t=xoxe-1347174488645-1612442201312-1573826913015-453545d9d1a501a4e497d7cb3f5eacde",
                "thumb_1024_w": 1024,
                "thumb_1024_h": 1024,
                "original_w": 2048,
                "original_h": 2048,
                "thumb_tiny": "AwAwADDQYnnGeKMtnGD+dG3c5IJHrz1pp3HPJ\/A0ASEYB5NMLELnDUYABw3zYzjNJnay5c4POMUAODZPR\/yp3Qjk0m\/PQEe9J3GDnnnmgBd2CaYW4460M3zbdpJJ4OOKaN44PQUAIoxuIUhjx0qTjqcZxigbtnKjp603eSoQoQzDjuKABySMBcgjkY60qYyuFxzk8UYfuSPTin4ORnFACfx8Y64oYjYc4GPU0FTk4PfNI6MxBGBjmgBokd8YjwpHJ3dDT14GcdeKRUcA\/d59KXawXA20AJIzbeMBu2eeaELk\/OAB29aV1ZsYxkUiCTI349cigD\/\/2Q==",
                "permalink": "https:\/\/opensciencest-4fn7856.slack.com\/files\/U01AGDAUB1S\/F01G7B8FWKH\/image.png",
                "permalink_public": "https:\/\/slack-files.com\/T01A754ECJZ-F01G7B8FWKH-83aff64a95",
                "is_starred": false,
                "has_rich_preview": false
            }
        ],
        "upload": false,
        "blocks": [
            {
                "type": "rich_text",
                "block_id": "MRI",
                "elements": [
                    {
                        "type": "rich_text_section",
                        "elements": [
                            {
                                "type": "text",
                                "text": "But I love them all!"
                            }
                        ]
                    }
                ]
            }
        ],
        "user": "U01AGDAUB1S",
        "display_as_bot": false,
        "ts": "1607630722.010600",
        "thread_ts": "1607544681.009800",
        "parent_user_id": "U01AA7U2ECA"
    },
    {
        "client_msg_id": "441725b2-d8bd-412a-9f4f-93acbad09472",
        "type": "message",
        "text": "Nice :smile: Yeah I've seen some come by years ago and just came across a bunch of new ones now, they are so awesome! :heart_eyes:",
        "user": "U01AA7U2ECA",
        "ts": "1607632428.011000",
        "team": "T01A754ECJZ",
        "user_team": "T01A754ECJZ",
        "source_team": "T01A754ECJZ",
        "user_profile": {
            "avatar_hash": "6e49adde29d9",
            "image_72": "https:\/\/avatars.slack-edge.com\/2020-10-05\/1420879323393_6e49adde29d9eae9ce72_72.jpg",
            "first_name": "Gwen",
            "real_name": "Gwen van der Wijk",
            "display_name": "Gwen",
            "team": "T01A754ECJZ",
            "name": "gwen.vanderwijk",
            "is_restricted": false,
            "is_ultra_restricted": false
        },
        "blocks": [
            {
                "type": "rich_text",
                "block_id": "K2Jr",
                "elements": [
                    {
                        "type": "rich_text_section",
                        "elements": [
                            {
                                "type": "text",
                                "text": "Nice "
                            },
                            {
                                "type": "emoji",
                                "name": "smile"
                            },
                            {
                                "type": "text",
                                "text": " Yeah I've seen some come by years ago and just came across a bunch of new ones now, they are so awesome! "
                            },
                            {
                                "type": "emoji",
                                "name": "heart_eyes"
                            }
                        ]
                    }
                ]
            }
        ],
        "thread_ts": "1607544681.009800",
        "parent_user_id": "U01AA7U2ECA"
    },
    {
        "type": "message",
        "text": "Some of them make my heart happy too!",
        "files": [
            {
                "id": "F01HC1ME6GY",
                "created": 1607632621,
                "timestamp": 1607632621,
                "name": "image.png",
                "title": "image.png",
                "mimetype": "image\/png",
                "filetype": "png",
                "pretty_type": "PNG",
                "user": "U01AGDAUB1S",
                "editable": false,
                "size": 701082,
                "mode": "hosted",
                "is_external": false,
                "external_type": "",
                "is_public": true,
                "public_url_shared": false,
                "display_as_bot": false,
                "username": "",
                "url_private": "https:\/\/files.slack.com\/files-pri\/T01A754ECJZ-F01HC1ME6GY\/image.png?t=xoxe-1347174488645-1612442201312-1573826913015-453545d9d1a501a4e497d7cb3f5eacde",
                "url_private_download": "https:\/\/files.slack.com\/files-pri\/T01A754ECJZ-F01HC1ME6GY\/download\/image.png?t=xoxe-1347174488645-1612442201312-1573826913015-453545d9d1a501a4e497d7cb3f5eacde",
                "thumb_64": "https:\/\/files.slack.com\/files-tmb\/T01A754ECJZ-F01HC1ME6GY-c48d39335f\/image_64.png?t=xoxe-1347174488645-1612442201312-1573826913015-453545d9d1a501a4e497d7cb3f5eacde",
                "thumb_80": "https:\/\/files.slack.com\/files-tmb\/T01A754ECJZ-F01HC1ME6GY-c48d39335f\/image_80.png?t=xoxe-1347174488645-1612442201312-1573826913015-453545d9d1a501a4e497d7cb3f5eacde",
                "thumb_360": "https:\/\/files.slack.com\/files-tmb\/T01A754ECJZ-F01HC1ME6GY-c48d39335f\/image_360.png?t=xoxe-1347174488645-1612442201312-1573826913015-453545d9d1a501a4e497d7cb3f5eacde",
                "thumb_360_w": 360,
                "thumb_360_h": 348,
                "thumb_480": "https:\/\/files.slack.com\/files-tmb\/T01A754ECJZ-F01HC1ME6GY-c48d39335f\/image_480.png?t=xoxe-1347174488645-1612442201312-1573826913015-453545d9d1a501a4e497d7cb3f5eacde",
                "thumb_480_w": 480,
                "thumb_480_h": 464,
                "thumb_160": "https:\/\/files.slack.com\/files-tmb\/T01A754ECJZ-F01HC1ME6GY-c48d39335f\/image_160.png?t=xoxe-1347174488645-1612442201312-1573826913015-453545d9d1a501a4e497d7cb3f5eacde",
                "thumb_720": "https:\/\/files.slack.com\/files-tmb\/T01A754ECJZ-F01HC1ME6GY-c48d39335f\/image_720.png?t=xoxe-1347174488645-1612442201312-1573826913015-453545d9d1a501a4e497d7cb3f5eacde",
                "thumb_720_w": 720,
                "thumb_720_h": 696,
                "original_w": 750,
                "original_h": 725,
                "thumb_tiny": "AwAuADC1NIyyEAnH1pA8hGd1OlIDtkiotyk8E1ZOrJN7DHzH8KXc394\/nTRjikLAdTT0Fqx29v7x\/OljkJkAyTUYZWORT4wPNXGKXQezGzxlpCRj86iEL55I\/OrMn+sNMJ9xS5epSm1ohqoQR06+tMeJiTgj86lz0IFIc54ptXJUmtURrEwOTj86lhUiVen50mcY6mnREmUelK1kNycnqJM4WRs5qLzQW5qzJbiRiSxFMFmoP3yaV2UlG2u40ODimtKAcYJqYW+D979KRrVWPLGm32JilfUhWXPUYqWJg0q4zQLQLyGJPvT44SjhiwOKL6ajklfQ\/9k=",
                "permalink": "https:\/\/opensciencest-4fn7856.slack.com\/files\/U01AGDAUB1S\/F01HC1ME6GY\/image.png",
                "permalink_public": "https:\/\/slack-files.com\/T01A754ECJZ-F01HC1ME6GY-045eba4cb3",
                "is_starred": false,
                "has_rich_preview": false
            }
        ],
        "upload": false,
        "blocks": [
            {
                "type": "rich_text",
                "block_id": "mAf",
                "elements": [
                    {
                        "type": "rich_text_section",
                        "elements": [
                            {
                                "type": "text",
                                "text": "Some of them make my heart happy too!"
                            }
                        ]
                    }
                ]
            }
        ],
        "user": "U01AGDAUB1S",
        "display_as_bot": false,
        "ts": "1607632628.011200",
        "thread_ts": "1607544681.009800",
        "parent_user_id": "U01AA7U2ECA"
    },
    {
        "client_msg_id": "ee48a5dc-7fca-4c65-b2c6-4ec8daa7716b",
        "type": "message",
        "text": "Yeah soo sweet!",
        "user": "U01AA7U2ECA",
        "ts": "1607632651.011600",
        "team": "T01A754ECJZ",
        "user_team": "T01A754ECJZ",
        "source_team": "T01A754ECJZ",
        "user_profile": {
            "avatar_hash": "6e49adde29d9",
            "image_72": "https:\/\/avatars.slack-edge.com\/2020-10-05\/1420879323393_6e49adde29d9eae9ce72_72.jpg",
            "first_name": "Gwen",
            "real_name": "Gwen van der Wijk",
            "display_name": "Gwen",
            "team": "T01A754ECJZ",
            "name": "gwen.vanderwijk",
            "is_restricted": false,
            "is_ultra_restricted": false
        },
        "blocks": [
            {
                "type": "rich_text",
                "block_id": "UM0",
                "elements": [
                    {
                        "type": "rich_text_section",
                        "elements": [
                            {
                                "type": "text",
                                "text": "Yeah soo sweet!"
                            }
                        ]
                    }
                ]
            }
        ],
        "thread_ts": "1607544681.009800",
        "parent_user_id": "U01AA7U2ECA"
    },
    {
        "type": "message",
        "text": "This is from the same creator :heart:",
        "files": [
            {
                "id": "F01H0QV76F3",
                "created": 1607632654,
                "timestamp": 1607632654,
                "name": "image.png",
                "title": "image.png",
                "mimetype": "image\/png",
                "filetype": "png",
                "pretty_type": "PNG",
                "user": "U01AA7U2ECA",
                "editable": false,
                "size": 53925,
                "mode": "hosted",
                "is_external": false,
                "external_type": "",
                "is_public": true,
                "public_url_shared": false,
                "display_as_bot": false,
                "username": "",
                "url_private": "https:\/\/files.slack.com\/files-pri\/T01A754ECJZ-F01H0QV76F3\/image.png?t=xoxe-1347174488645-1612442201312-1573826913015-453545d9d1a501a4e497d7cb3f5eacde",
                "url_private_download": "https:\/\/files.slack.com\/files-pri\/T01A754ECJZ-F01H0QV76F3\/download\/image.png?t=xoxe-1347174488645-1612442201312-1573826913015-453545d9d1a501a4e497d7cb3f5eacde",
                "thumb_64": "https:\/\/files.slack.com\/files-tmb\/T01A754ECJZ-F01H0QV76F3-f570a47131\/image_64.png?t=xoxe-1347174488645-1612442201312-1573826913015-453545d9d1a501a4e497d7cb3f5eacde",
                "thumb_80": "https:\/\/files.slack.com\/files-tmb\/T01A754ECJZ-F01H0QV76F3-f570a47131\/image_80.png?t=xoxe-1347174488645-1612442201312-1573826913015-453545d9d1a501a4e497d7cb3f5eacde",
                "thumb_360": "https:\/\/files.slack.com\/files-tmb\/T01A754ECJZ-F01H0QV76F3-f570a47131\/image_360.png?t=xoxe-1347174488645-1612442201312-1573826913015-453545d9d1a501a4e497d7cb3f5eacde",
                "thumb_360_w": 280,
                "thumb_360_h": 280,
                "thumb_160": "https:\/\/files.slack.com\/files-tmb\/T01A754ECJZ-F01H0QV76F3-f570a47131\/image_160.png?t=xoxe-1347174488645-1612442201312-1573826913015-453545d9d1a501a4e497d7cb3f5eacde",
                "original_w": 280,
                "original_h": 280,
                "thumb_tiny": "AwAwADDTyKMimscUiuCSmcso5oAduHqKNw9ajkbYueeBkYFKvODg84oAkyKM0wt82M96f3FACEA9aAoHTNLTFYs\/tigB20HtRilooATaM570uKKKACmIpUknFOpKAFozSUuKADNJS4paAP\/Z",
                "permalink": "https:\/\/opensciencest-4fn7856.slack.com\/files\/U01AA7U2ECA\/F01H0QV76F3\/image.png",
                "permalink_public": "https:\/\/slack-files.com\/T01A754ECJZ-F01H0QV76F3-6507abf089",
                "is_starred": false,
                "has_rich_preview": false
            }
        ],
        "upload": false,
        "blocks": [
            {
                "type": "rich_text",
                "block_id": "+R3",
                "elements": [
                    {
                        "type": "rich_text_section",
                        "elements": [
                            {
                                "type": "text",
                                "text": "This is from the same creator "
                            },
                            {
                                "type": "emoji",
                                "name": "heart"
                            }
                        ]
                    }
                ]
            }
        ],
        "user": "U01AA7U2ECA",
        "display_as_bot": false,
        "ts": "1607632668.011800",
        "thread_ts": "1607544681.009800",
        "parent_user_id": "U01AA7U2ECA"
    },
    {
        "client_msg_id": "e7a223ff-457e-4352-9f14-2aa2666711be",
        "type": "message",
        "text": "Love it!",
        "user": "U01AGDAUB1S",
        "ts": "1607632891.012200",
        "team": "T01A754ECJZ",
        "user_team": "T01A754ECJZ",
        "source_team": "T01A754ECJZ",
        "user_profile": {
            "avatar_hash": "81afe241c15d",
            "image_72": "https:\/\/avatars.slack-edge.com\/2020-10-02\/1397872543414_81afe241c15daae264e5_72.jpg",
            "first_name": "Brittany",
            "real_name": "Brittany Lindsay",
            "display_name": "Brittany",
            "team": "T01A754ECJZ",
            "name": "bllindsa",
            "is_restricted": false,
            "is_ultra_restricted": false
        },
        "blocks": [
            {
                "type": "rich_text",
                "block_id": "UGz+N",
                "elements": [
                    {
                        "type": "rich_text_section",
                        "elements": [
                            {
                                "type": "text",
                                "text": "Love it!"
                            }
                        ]
                    }
                ]
            }
        ],
        "thread_ts": "1607544681.009800",
        "parent_user_id": "U01AA7U2ECA"
    }
]